{"spx": {"price": "7,577", "change": 0.43}, "ftse": {"price": "10,537", "change": 0.17}, "dax": {"price": "25,008", "change": -0.55}, "omxspi": {"price": "1,099", "change": 0.13}, "omxs30": {"price": "3,163", "change": 0.02}, "nikkei": {"price": "68,752", "change": 1.48}, "bchusd": {"price": "235.65", "change": -0.46}, "eurusd": {"price": "1.1435"}, "gbpusd": {"price": "1.3444"}, "eurchf": {"price": "0.9242"}, "eurjpy": {"price": "185.43"}, "usdchf": {"price": "0.8084"}, "usdjpy": {"price": "162.2"}, "usdsek": {"price": "9.6495"}, "usddkk": {"price": "6.538"}, "usdnok": {"price": "9.7015"}, "usdcop": {"price": "3245.28"}, "sekcop": {"price": "336"}}