{"spx": {"price": "7,444", "change": 0.58}, "ftse": {"price": "10,325", "change": 0.58}, "dax": {"price": "24,137", "change": 0.76}, "omxspi": {"price": "1,064", "change": 0.19}, "omxs30": {"price": "3,048", "change": 0.05}, "nikkei": {"price": "63,272", "change": 0.89}, "bchusd": {"price": "434.44", "change": -1.21}, "eurusd": {"price": "1.1721"}, "gbpusd": {"price": "1.3528"}, "eurchf": {"price": "0.9157"}, "eurjpy": {"price": "184.89"}, "usdchf": {"price": "0.7815"}, "usdjpy": {"price": "157.79"}, "usdsek": {"price": "9.3225"}, "usddkk": {"price": "6.3769"}, "usdnok": {"price": "9.1632"}, "usdcop": {"price": "3777.97"}, "sekcop": {"price": "405"}}