{"spx": {"price": "7,608", "change": 0.1}, "ftse": {"price": "10,374", "change": 0.33}, "dax": {"price": "25,124", "change": 0.48}, "omxspi": {"price": "1,095", "change": 1.49}, "omxs30": {"price": "3,150", "change": 1.79}, "nikkei": {"price": "66,734", "change": -0.41}, "bchusd": {"price": "284.69", "change": -2.93}, "eurusd": {"price": "1.1627"}, "gbpusd": {"price": "1.3461"}, "eurchf": {"price": "0.9156"}, "eurjpy": {"price": "185.9"}, "usdchf": {"price": "0.7878"}, "usdjpy": {"price": "159.95"}, "usdsek": {"price": "9.3223"}, "usddkk": {"price": "6.43"}, "usdnok": {"price": "9.291"}, "usdcop": {"price": "3578.42"}, "sekcop": {"price": "384"}}