{"spx": {"price": "7,473", "change": 0.37}, "ftse": {"price": "10,466", "change": 0.22}, "dax": {"price": "24,889", "change": 1.15}, "omxspi": {"price": "1,098", "change": 0.98}, "omxs30": {"price": "3,146", "change": 0.97}, "nikkei": {"price": "63,339", "change": 2.65}, "bchusd": {"price": "348.95", "change": -1.75}, "eurusd": {"price": "1.162"}, "gbpusd": {"price": "1.3469"}, "eurchf": {"price": "0.9128"}, "eurjpy": {"price": "184.84"}, "usdchf": {"price": "0.7839"}, "usdjpy": {"price": "158.75"}, "usdsek": {"price": "9.3646"}, "usddkk": {"price": "6.4155"}, "usdnok": {"price": "9.2259"}, "usdcop": {"price": "3683.52"}, "sekcop": {"price": "393"}}