{"spx": {"price": "7,564", "change": 0.58}, "ftse": {"price": "10,426", "change": -0.75}, "dax": {"price": "25,092", "change": -0.34}, "omxspi": {"price": "1,090", "change": -1.05}, "omxs30": {"price": "3,124", "change": -1.01}, "nikkei": {"price": "65,892", "change": 1.82}, "bchusd": {"price": "300.78", "change": -0.25}, "eurusd": {"price": "1.1659"}, "gbpusd": {"price": "1.3449"}, "eurchf": {"price": "0.9128"}, "eurjpy": {"price": "185.62"}, "usdchf": {"price": "0.7831"}, "usdjpy": {"price": "159.26"}, "usdsek": {"price": "9.2385"}, "usddkk": {"price": "6.4102"}, "usdnok": {"price": "9.2437"}, "usdcop": {"price": "3637.88"}, "sekcop": {"price": "394"}}