{"spx": {"price": "6,824.66", "change": 0.62}, "ftse": {"price": "10,636.90", "change": 0.54}, "dax": {"price": "23,836.41", "change": 0.33}, "omxspi": {"price": "1,080.04", "change": 1.0}, "omxs30": {"price": "3,108.32", "change": 0.94}, "nikkei": {"price": "56,924.11", "change": 1.89}, "eurusd": {"price": "1.1704"}, "gbpusd": {"price": "1.3433"}, "eurchf": {"price": "0.9244"}, "eurjpy": {"price": "186.32"}, "usdchf": {"price": "0.7901"}, "usdjpy": {"price": "159.25"}, "usdsek": {"price": "9.2898"}, "usddkk": {"price": "6.3861"}, "usdnok": {"price": "9.4934"}}