{"spx": {"price": "7,357", "change": -0.01}, "ftse": {"price": "10,530", "change": 0.65}, "dax": {"price": "24,995", "change": 1.03}, "omxspi": {"price": "1,095", "change": 0.78}, "omxs30": {"price": "3,181", "change": 1.08}, "nikkei": {"price": "72,366", "change": 4.46}, "bchusd": {"price": "188.11", "change": -1.06}, "eurusd": {"price": "1.1379"}, "gbpusd": {"price": "1.3199"}, "eurchf": {"price": "0.9206"}, "eurjpy": {"price": "183.92"}, "usdchf": {"price": "0.809"}, "usdjpy": {"price": "161.74"}, "usdsek": {"price": "9.7145"}, "usddkk": {"price": "6.5713"}, "usdnok": {"price": "9.8313"}, "usdcop": {"price": "3431.5"}, "sekcop": {"price": "353"}}