{"spx": {"price": "7,504", "change": -0.45}, "ftse": {"price": "10,666", "change": 0.13}, "dax": {"price": "25,465", "change": -1.37}, "omxspi": {"price": "1,109", "change": -0.71}, "omxs30": {"price": "3,205", "change": -0.93}, "nikkei": {"price": "67,102", "change": -1.91}, "bchusd": {"price": "236.42", "change": -1.22}, "eurusd": {"price": "1.1426"}, "gbpusd": {"price": "1.3365"}, "eurchf": {"price": "0.9218"}, "eurjpy": {"price": "185.21"}, "usdchf": {"price": "0.807"}, "usdjpy": {"price": "162.13"}, "usdsek": {"price": "9.6777"}, "usddkk": {"price": "6.5438"}, "usdnok": {"price": "9.7838"}, "usdcop": {"price": "3331.84"}, "sekcop": {"price": "344"}}