{"spx": {"price": "6,782.81", "change": 2.51}, "ftse": {"price": "10,608.88", "change": 2.51}, "dax": {"price": "24,080.63", "change": 5.06}, "omxspi": {"price": "1,074.22", "change": 3.96}, "omxs30": {"price": "3,094.16", "change": 4.26}, "nikkei": {"price": "56,308.42", "change": 5.21}, "eurusd": {"price": "1.1666"}, "gbpusd": {"price": "1.34"}, "eurchf": {"price": "0.9228"}, "eurjpy": {"price": "184.93"}, "usdchf": {"price": "0.7912"}, "usdjpy": {"price": "158.57"}, "usdsek": {"price": "9.314"}, "usddkk": {"price": "6.406"}, "usdnok": {"price": "9.5687"}}