{"spx": {"price": "7,387", "change": -0.26}, "ftse": {"price": "10,227", "change": -1.41}, "dax": {"price": "24,433", "change": -0.74}, "omxspi": {"price": "1,071", "change": -1.26}, "omxs30": {"price": "3,070", "change": -1.21}, "nikkei": {"price": "64,020", "change": -2.09}, "bchusd": {"price": "200.04", "change": -1.68}, "eurusd": {"price": "1.1558"}, "gbpusd": {"price": "1.3395"}, "eurchf": {"price": "0.9219"}, "eurjpy": {"price": "185.27"}, "usdchf": {"price": "0.7979"}, "usdjpy": {"price": "160.34"}, "usdsek": {"price": "9.4574"}, "usddkk": {"price": "6.4677"}, "usdnok": {"price": "9.4958"}, "usdcop": {"price": "3566.37"}, "sekcop": {"price": "377"}}