{"spx": {"price": "6,601.22", "change": 1.11}, "ftse": {"price": "10,364.79", "change": 1.85}, "dax": {"price": "23,298.89", "change": 2.73}, "omxspi": {"price": "1,048.77", "change": 2.62}, "omxs30": {"price": "3,006.37", "change": 2.63}, "nikkei": {"price": "53,739.68", "change": 4.63}, "eurusd": {"price": "1.1538"}, "gbpusd": {"price": "1.3233"}, "eurchf": {"price": "0.9225"}, "eurjpy": {"price": "183.38"}, "usdchf": {"price": "0.7995"}, "usdjpy": {"price": "158.93"}, "usdsek": {"price": "9.4857"}, "usddkk": {"price": "6.4684"}, "usdnok": {"price": "9.7145"}}