{"spx": {"price": "7,580", "change": 0.22}, "ftse": {"price": "10,409", "change": -0.16}, "dax": {"price": "25,105", "change": 0.05}, "omxspi": {"price": "1,095", "change": 0.5}, "omxs30": {"price": "3,138", "change": 0.45}, "nikkei": {"price": "66,330", "change": 2.5}, "bchusd": {"price": "300.92", "change": -0.75}, "eurusd": {"price": "1.1658"}, "gbpusd": {"price": "1.3452"}, "eurchf": {"price": "0.91"}, "eurjpy": {"price": "185.7"}, "usdchf": {"price": "0.7803"}, "usdjpy": {"price": "159.37"}, "usdsek": {"price": "9.2215"}, "usddkk": {"price": "6.4114"}, "usdnok": {"price": "9.2262"}, "usdcop": {"price": "3665.87"}, "sekcop": {"price": "398"}}