{"spx": {"price": "7,137.66", "change": 0.42}, "ftse": {"price": "10,404.22", "change": -0.61}, "dax": {"price": "24,131.93", "change": -0.2}, "omxspi": {"price": "1,085.52", "change": -0.79}, "omxs30": {"price": "3,108.47", "change": -0.73}, "nikkei": {"price": "59,716.18", "change": 0.91}, "eurusd": {"price": "1.1714"}, "gbpusd": {"price": "1.35"}, "eurchf": {"price": "0.92"}, "eurjpy": {"price": "186.73"}, "usdchf": {"price": "0.7857"}, "usdjpy": {"price": "159.47"}, "usdsek": {"price": "9.242"}, "usddkk": {"price": "6.381"}, "usdnok": {"price": "9.3406"}, "usdcop": {"price": "3547.27"}, "sekcop": {"price": "384"}}